LICENSE
README.md
pyproject.toml
setup.cfg
setup.py
stellaspark_utils/__init__.py
stellaspark_utils/conftest.py
stellaspark_utils/db.py
stellaspark_utils/text.py
stellaspark_utils.egg-info/PKG-INFO
stellaspark_utils.egg-info/SOURCES.txt
stellaspark_utils.egg-info/dependency_links.txt
stellaspark_utils.egg-info/not-zip-safe
stellaspark_utils.egg-info/requires.txt
stellaspark_utils.egg-info/top_level.txt