Metadata-Version: 2.1
Name: stellaspark-utils
Version: 3.0
Summary: A collection of python utilities for StellaSpark Nexus Digital Twin
Home-page: https://github.com/StellaSpark/stellaspark_utils
Download-URL: https://github.com/StellaSpark/stellaspark_utils/archive/v3.0.tar.gz
Author: StellaSpark
Author-email: support@stellaspark.com
Maintainer: StellaSpark
Maintainer-email: support@stellaspark.com
License: MIT
Keywords: stellaspark,nexus,utils,calculation,python
Classifier: Development Status :: 5 - Production/Stable
Classifier: Intended Audience :: Developers
Classifier: Intended Audience :: Information Technology
Classifier: Intended Audience :: Science/Research
Classifier: License :: OSI Approved :: MIT License
Classifier: Natural Language :: English
Classifier: Programming Language :: Python :: 3
Classifier: Programming Language :: Python :: 3.7
Classifier: Programming Language :: Python :: 3.8
Classifier: Programming Language :: Python :: 3.9
Classifier: Programming Language :: Python :: 3.10
Classifier: Programming Language :: Python :: 3.11
Classifier: Programming Language :: Python :: 3.12
Classifier: Topic :: Software Development :: Build Tools
Requires-Python: >=3.7, <=3.12.9
Provides-Extra: test
License-File: LICENSE
